vital_agent_container_client/__init__.py
vital_agent_container_client/aimp_message_handler_inf.py
vital_agent_container_client/vital_agent_container_client.py
vital_agent_container_client-0.0.8.dist-info/licenses/LICENSE
vital_agent_container_client-0.0.8.dist-info/METADATA
vital_agent_container_client-0.0.8.dist-info/WHEEL
vital_agent_container_client-0.0.8.dist-info/top_level.txt
vital_agent_container_client-0.0.8.dist-info/RECORD
