Metadata-Version: 2.4
Name: vital-agent-container-client
Version: 0.0.8
Summary: Vital Agent Container Client
Home-page: https://github.com/vital-ai/vital-agent-container-client
Author: Marc Hadfield
Author-email: marc@vital.ai
License: Apache License 2.0
Classifier: Programming Language :: Python :: 3.12
Classifier: License :: OSI Approved :: Apache Software License
Classifier: Operating System :: OS Independent
Requires-Python: >=3.12
License-File: LICENSE
Requires-Dist: vital-ai-vitalsigns>=0.1.32
Requires-Dist: vital-ai-domain>=0.1.7
Requires-Dist: six
Requires-Dist: pyyaml
Requires-Dist: websockets
Requires-Dist: httpx
Provides-Extra: dev
Requires-Dist: twine; extra == "dev"
Requires-Dist: wheel>=0.43.0; extra == "dev"
Dynamic: author
Dynamic: author-email
Dynamic: classifier
Dynamic: description
Dynamic: description-content-type
Dynamic: home-page
Dynamic: license
Dynamic: license-file
Dynamic: provides-extra
Dynamic: requires-dist
Dynamic: requires-python
Dynamic: summary
